cloaked_ai/__init__.py
cloaked_ai/libcloaked_ai.dylib
cloaked_ai-0.4.3.dist-info/METADATA
cloaked_ai-0.4.3.dist-info/WHEEL
cloaked_ai-0.4.3.dist-info/licenses/LICENSE.txt
cloaked_ai-0.4.3.dist-info/RECORD
