Metadata-Version: 2.1
Name: cloaked-ai
Version: 0.4.3
Summary: Python bindings to the IronCore Labs Cloaked AI SDK. Used for encrypting and decrypting embeddings and their related metadata.
Project-URL: Homepage, https://ironcorelabs.com
Author-email: IronCore Labs <info@ironcorelabs.com>
License-File: LICENSE.txt
Classifier: License :: OSI Approved :: GNU Affero General Public License v3 or later (AGPLv3+)
Classifier: Operating System :: MacOS
Classifier: Operating System :: POSIX :: Linux
Classifier: Programming Language :: Python :: 3
Requires-Python: >=3.7
